ara_api_web/__init__.py
ara_api_web/__main__.py
ara_api_web/_core/__init__.py
ara_api_web/_core/app.py
ara_api_web/_core/dependencies.py
ara_api_web/_core/server.py
ara_api_web/_core/models/__init__.py
ara_api_web/_core/models/requests.py
ara_api_web/_core/models/responses.py
ara_api_web/_core/routers/__init__.py
ara_api_web/_core/routers/health.py
ara_api_web/_core/routers/status.py
ara_api_web/_core/routers/api/__init__.py
ara_api_web/_core/routers/api/msp.py
ara_api_web/_core/routers/api/navigation.py
ara_api_web/_core/routers/api/vision.py
ara_api_web/_utils/__init__.py
ara_api_web/_utils/config.py
ara_api_web/_utils/decorators.py
ara_api_web/_utils/logger.py
ara_api_web/_utils/rest_helpers.py
ara_api_web/_utils/ui.py
ara_api_web/_utils/communication/__init__.py
ara_api_web/_utils/communication/gRPCSync.py
ara_api_web/_utils/communication/grpc/msp_pb2.py
ara_api_web/_utils/communication/grpc/msp_pb2_grpc.py
ara_api_web/_utils/communication/grpc/navigation_pb2.py
ara_api_web/_utils/communication/grpc/navigation_pb2_grpc.py
ara_api_web/_utils/communication/grpc/vision_pb2.py
ara_api_web/_utils/communication/grpc/vision_pb2_grpc.py
ara_api_web/_utils/communication/grpc/messages/base_msg_pb2.py
ara_api_web/_utils/communication/grpc/messages/base_msg_pb2_grpc.py
ara_api_web/_utils/communication/grpc/messages/msp_msg_pb2.py
ara_api_web/_utils/communication/grpc/messages/msp_msg_pb2_grpc.py
ara_api_web/_utils/communication/grpc/messages/nav_msg_pb2.py
ara_api_web/_utils/communication/grpc/messages/nav_msg_pb2_grpc.py
ara_api_web/_utils/communication/grpc/messages/vision_msg_pb2.py
ara_api_web/_utils/communication/grpc/messages/vision_msg_pb2_grpc.py
ara_api_web-1.1.0.dist-info/METADATA
ara_api_web-1.1.0.dist-info/WHEEL
ara_api_web-1.1.0.dist-info/entry_points.txt
ara_api_web-1.1.0.dist-info/licenses/LICENSE
ara_api_web-1.1.0.dist-info/RECORD
