Metadata-Version: 2.4
Name: ara-api-web
Version: 1.1.0
Summary: Web interface for ARA API
Author-email: Alexander Kleimenov <nequamy@gmail.com>
License: MIT
License-File: LICENSE
Keywords: API,ARA,drones,robotics
Classifier: Development Status :: 4 - Beta
Classifier: Intended Audience :: Developers
Classifier: License :: OSI Approved :: MIT License
Classifier: Operating System :: MacOS
Classifier: Operating System :: Microsoft :: Windows
Classifier: Operating System :: Unix
Classifier: Programming Language :: Python
Classifier: Programming Language :: Python :: 3
Classifier: Programming Language :: Python :: 3.10
Classifier: Programming Language :: Python :: 3.11
Classifier: Programming Language :: Python :: 3.12
Classifier: Programming Language :: Python :: 3.13
Classifier: Topic :: Scientific/Engineering
Classifier: Topic :: Software Development
Requires-Python: >=3.8
Requires-Dist: fastapi<0.122.0,>=0.100.0; python_version < '3.9'
Requires-Dist: fastapi<0.122.0,>=0.121.1; python_version >= '3.9'
Requires-Dist: grpcio-tools==1.66.2
Requires-Dist: grpcio==1.69.0
Requires-Dist: rich>=14.2.0
Requires-Dist: uvicorn<0.28.0,>=0.20.0; python_version == '3.8'
Requires-Dist: uvicorn<0.40.0,>=0.30.0; python_version >= '3.9'
